hgdl/__init__.py
hgdl/_version.py
hgdl/hgdl.py
hgdl/meta_data.py
hgdl/misc.py
hgdl/optima.py
hgdl/support_functions.py
hgdl/global_methods/__init__.py
hgdl/global_methods/global_optimizer.py
hgdl/local_methods/__init__.py
hgdl/local_methods/bump_function.py
hgdl/local_methods/dNewton.py
hgdl/local_methods/local_optimizer.py
hgdl-2.3.3.dist-info/METADATA
hgdl-2.3.3.dist-info/WHEEL
hgdl-2.3.3.dist-info/licenses/AUTHORS.rst
hgdl-2.3.3.dist-info/licenses/LICENSE
hgdl-2.3.3.dist-info/RECORD
