Metadata-Version: 2.4
Name: hgdl
Version: 2.3.3
Summary: HGDL Optimization
Project-URL: Homepage, https://github.com/lbl-camera/hgdl
Project-URL: Documentation, https://hgdl.readthedocs.io/
Project-URL: Repository, https://github.com/lbl-camera/hgdl.git
Project-URL: Bug Tracker, https://github.com/lbl-camera/hgdl/issues
Project-URL: Changelog, https://github.com/lbl-camera/hgdl/commits/master/
Author-email: Marcus Michael Noack <MarcusNoack@lbl.gov>, "Ronald J. Pandolfi" <ronpandolfi@lbl.gov>
Maintainer-email: Marcus Michael Noack <MarcusNoack@lbl.gov>, "Ronald J. Pandolfi" <ronpandolfi@lbl.gov>
License: *** License Agreement ***
License-File: AUTHORS.rst
License-File: LICENSE
Keywords: adaptive,autonomous,gui,qt,self driving
Classifier: Development Status :: 5 - Production/Stable
Classifier: Intended Audience :: Developers
Classifier: License :: OSI Approved :: BSD License
Classifier: Natural Language :: English
Classifier: Programming Language :: Python :: 3
Classifier: Programming Language :: Python :: 3.10
Classifier: Programming Language :: Python :: 3.11
Classifier: Programming Language :: Python :: 3.12
Requires-Python: >=3.10
Requires-Dist: dask~=2025.5.1
Requires-Dist: distributed~=2025.5.1
Requires-Dist: loguru
Requires-Dist: numpy~=2.2.6
Requires-Dist: scipy~=1.16.0
Requires-Dist: wheel
Provides-Extra: docs
Requires-Dist: autodocs; extra == 'docs'
Requires-Dist: jupytext; extra == 'docs'
Requires-Dist: myst-nb; extra == 'docs'
Requires-Dist: myst-parser; extra == 'docs'
Requires-Dist: sphinx; extra == 'docs'
Requires-Dist: sphinx-panels; extra == 'docs'
Requires-Dist: sphinx-rtd-theme; extra == 'docs'
Provides-Extra: plotting
Requires-Dist: bokeh; extra == 'plotting'
Requires-Dist: matplotlib; extra == 'plotting'
Requires-Dist: plotly; extra == 'plotting'
Provides-Extra: tests
Requires-Dist: codecov; extra == 'tests'
Requires-Dist: pytest; extra == 'tests'
Requires-Dist: pytest-cov; extra == 'tests'
